video2image/__init__.py
video2image/converter.py
video2image-1.3.0.dist-info/LICENSE
video2image-1.3.0.dist-info/METADATA
video2image-1.3.0.dist-info/WHEEL
video2image-1.3.0.dist-info/entry_points.txt
video2image-1.3.0.dist-info/top_level.txt
video2image-1.3.0.dist-info/RECORD
